{
  "group_id": "Central Tax::73/2020",
  "tax_type": "Central Tax",
  "notification_no": "73/2020",
  "documents": [
    {
      "document_nature": "original",
      "issued_on": "2020-10-01",
      "identity_source": "pdf",
      "file_path": "data\\notifications\\Central tax\\Central tax 2020\\notfctn-73-central-tax-english-2020.pdf"
    }
  ],
  "composite_text": "[ORIGINAL | Issued: 2020-10-01 | Source: notfctn-73-central-tax-english-2020.pdf]\n[PAGE 1]\n[To be published in the Gazette of India, Extraordinary, Part II, Section 3, Sub-section\n(i)]\nGovernment of India\nMinistry of Finance\n(Department of Revenue)\nCentral Board of Indirect Taxes and Customs\nNotification No. 73/2020 – Central Tax\nNew Delhi, the 1st October, 2020\nG.S.R......(E). - In exercise of the powers conferred by section 148 of the Central Goods and\nServices Tax Act, 2017 (12 of 2017), the Central Government, on the recommendations of\nthe Council, hereby notifies the registered persons required to prepare the tax invoice in the\nmanner specified under sub-rule (4) of rule 48 of the Central Goods and Services Tax Rules,\n2017, who have prepared tax invoice in a manner other than the said manner, as the class of\npersons who shall, during the period from the 1st day of October, 2020 to the 31st day of\nOctober, 2020, follow the special procedure such that the said persons shall obtain an Invoice\nReference Number (IRN) for such invoice by uploading specified particulars in FORM GST\nINV-01 on the Common Goods and Services Tax Electronic Portal, within thirty days from\nthe date of such invoice, failing which the same shall not be treated as an invoice.\n[F. No. CBEC 20/16/09/2019-GST (Part – I)]\n(Pramod Kumar)\nDirector, Government of India",
  "latest_effective_date": "2020-10-01",
  "file_paths": [
    "data\\notifications\\Central tax\\Central tax 2020\\notfctn-73-central-tax-english-2020.pdf"
  ]
}