{
  "group_id": "Central Tax::21/2017",
  "tax_type": "Central Tax",
  "notification_no": "21/2017",
  "documents": [
    {
      "document_nature": "original",
      "issued_on": "2017-08-22",
      "identity_source": "pdf",
      "file_path": "data\\notifications\\Central Tax (Rate)\\2017\\download (17).pdf"
    },
    {
      "document_nature": "original",
      "issued_on": null,
      "identity_source": "pdf",
      "file_path": "data\\notifications\\Central tax\\Central Tax 2017\\download (20).pdf"
    }
  ],
  "composite_text": "[ORIGINAL | Issued: 2017-08-22 | Source: download (17).pdf]\n[PAGE 1]\n[TO BE PUBLISHED IN THE GAZZETE OF INDIA, EXTRAORDINARY, PART II, SECTION\n3, SUB-SECTION (i)]\nGovernment of India\nMinistry of Finance\n(Department of Revenue)\nNotification No. 21/2017- Central Tax (Rate)\nNew Delhi, the 22nd August, 2017\nG.S.R......(E).- In exercise of the powers conferred by sub-section (1) of section 11 of the\nCentral Goods and Services Tax Act, 2017 (12 of 2017), the Central Government, on being\nsatisfied that it is necessary in the public interest so to do, on the recommendations of the\nCouncil, hereby makes the following amendments in the notification of the Government of\nIndia, in the Ministry of Finance (Department of Revenue), No.12/2017- Central Tax (Rate),\ndated the 28th June, 2017, published in the Gazette of India, Extraordinary, Part II, Section 3,\nSub-section (i), vide number G.S.R. 691(E), dated the 28th June, 2017, namely:-\nIn the said notification,-\n(i) in the Table,-\n(a) after serial number 9 and the entries relating thereto, the following shall be inserted\nnamely:-\n(1) (2) (3) (4) (5)\n“9A Chapter 99 Services provided by and to Provided that Director\nFédération Internationale de (Sports), Ministry of\nFootball Association (FIFA) and Youth Affairs and\nits subsidiaries directly or Sports certifies that\nindirectly related to any of the Nil the services are\nevents under FIFA U-17 World directly or indirectly\nCup 2017 to be hosted in India. related to any of the\nevents under FIFA U-\n17 World Cup 2017.”;\n(b) after serial number 11 and the entries relating thereto, the following shall be inserted\nnamely:-\n(1) (2) (3) (4) (5)\n“11A Heading 9961 Service provided by Fair Price\nor Shops to Central Government by Nil Nil\nHeading 9962 way of sale of wheat, rice and\n1\n\n[PAGE 2]\ncoarse grains under Public\nDistribution System(PDS) against\nconsideration in the form of\ncommission or margin.\n11B Heading 9961 Service provided by Fair Price\nor Shops to State Governments or\nHeading 9962 Union territories by way of sale\nof kerosene, sugar, edible oil, etc. Nil Nil”;\nunder Public Distribution System\n(PDS) against consideration in the\nform of commission or margin.\n(c) against serial number 35, in column (3),-\n(A) in item (h), for the words “Weather Based Crop Insurance Scheme or the Modified\nNational Agricultural Insurance Scheme”, the words, brackets and letters\n“Restructured Weather Based Crop Insurance Scheme (RWCIS)”, shall be substituted;\n(B) in item (j), for the words “National Agricultural Insurance Scheme (Rashtriya Krishi\nBima Yojana)”, the words, brackets and letters “Pradhan Mantri Fasal BimaYojana\n(PMFBY)”, shall be substituted;\n(ii) in paragraph 3, in the Explanation, after clause (ii), the following clause shall be inserted,\nnamely:-\n“(iii) A “Limited Liability Partnership” formed and registered under the provisions of\nthe Limited Liability Partnership Act, 2008 (6 of 2009) shall also be considered as a\npartnership firm or a firm.”.\n[F. No.354/173/2017 -TRU]\n(Ruchi Bisht)\nUnder Secretary to the Government of India\nNote:-The principal notification was published in the Gazette of India, Extraordinary, vide\nnotification No. 12/2017 - Central Tax (Rate), dated the 28th June, 2017, vide number G.S.R.\n691 (E), dated the 28th June, 2017.\n2\n\n[ORIGINAL | Issued: UNKNOWN | Source: download (20).pdf]\n[PAGE 1]\n[To be published in the Gazette of India, Extraordinary, Part II, Section 3, Sub-section\n(i)]\nGovernment of India\nMinistry of Finance\n(Department of Revenue)\n(Central Board of Excise and Customs)\nNotification No. 21/2017 – Central Tax\nNew Delhi, 08th August, 2017\nG.S.R. …..(E).— In exercise of the powers conferred by sub-rule (5) of rule 61 of the Central\nGoods and Services Tax Rules, 2017, read with section 168 of the Central Goods and\nServices Act, 2017 (12 of 2017), the Commissioner, on the recommendations of the Council,\nspecifies that the return for the month as specified in column (2) of the Table below shall be\nfurnished in FORM GSTR-3B electronically through the common portal before the dates as\nspecified in the corresponding entry in column (3) of the said Table, namely:-\nTable\nSerial Number Month Date for filing of GSTR-3B\n(1) (2) (3)\n1. July, 2017 20th August, 2017\n2. August, 2017 20th September, 2017.\n2. This notification shall come into force with effect from the 8th day of August, 2017.\n[F. No.349 /74 /2017-GST(Pt.)]\n(Dr. Sreeparvathy S.L.)\nUnder Secretary to the Government of India",
  "latest_effective_date": "2017-08-22",
  "file_paths": [
    "data\\notifications\\Central Tax (Rate)\\2017\\download (17).pdf",
    "data\\notifications\\Central tax\\Central Tax 2017\\download (20).pdf"
  ]
}