{
  "group_id": "Central Tax::04/2021",
  "tax_type": "Central Tax",
  "notification_no": "04/2021",
  "documents": [
    {
      "document_nature": "amendment",
      "issued_on": "2021-02-28",
      "identity_source": "pdf",
      "file_path": "data\\notifications\\Central tax\\Central Tax 2021\\notfctn-04-central-tax-english-2021.pdf"
    },
    {
      "document_nature": "original",
      "issued_on": "2021-06-14",
      "identity_source": "pdf",
      "file_path": "data\\notifications\\Central Tax (Rate)\\2021\\download (2).pdf"
    }
  ],
  "composite_text": "[AMENDMENT | Issued: 2021-02-28 | Source: notfctn-04-central-tax-english-2021.pdf]\n[PAGE 1]\n[To be published in the Gazette of India, Extraordinary, Part II, Section 3, Sub-\nsection (i)]\nGovernment of India\nMinistry of Finance\n(Department of Revenue)\nCentral Board of Indirect Taxes and Customs\nNotification No. 04/2021 – Central Tax\nNew Delhi, the 28th February, 2021\nG.S.R.....(E).– In exercise of the powers conferred by sub-section (1) of section 44 of the\nCentral Goods and Services Tax Act, 2017 (12 of 2017), read with rule 80 of the Central\nGoods and Services Tax Rules, 2017, the Commissioner, on the recommendations of the\nCouncil, hereby makes the following amendment in the notification of the Government of\nIndia in the Ministry of Finance (Department of Revenue), No. 95/2020 - Central Tax, dated\nthe 30th December, 2020 published in the Gazette of India, Extraordinary, Part II, Section 3,\nSub-section (i), vide number G.S.R. 809(E), dated the 30th December, 2020, namely:-\nIn the said notification, for the figures “28.02.2021”, the figures “31.03.2021” shall be\nsubstituted.\n[F. No. CBEC-20/06/13/2020-GST]\n(Rajeev Ranjan)\nUnder Secretary to the Government of India\nNote: The principal notification No. 95/2020 - Central Tax, dated the 30th December, 2020,\nwas published in the Gazette of India, Extraordinary, vide number 809(E), dated the 30th\nDecember, 2020.\n\n[ORIGINAL | Issued: 2021-06-14 | Source: download (2).pdf]\n[PAGE 1]\n[TO BE PUBLISHED IN THE GAZZETE OF INDIA, EXTRAORDINARY, PART II, SECTION 3, SUB-\nSECTION (i)]\nGovernment of India\nMinistry of Finance\n(Department of Revenue)\nNotification No. 04/2021- Central Tax (Rate)\nNew Delhi, the 14th June, 2021\nG.S.R......(E).- In exercise of the powers conferred by sub-section (1), sub-section (3) and sub-section (4) of\nsection 9, sub-section (1) of section 11, sub-section (5) of section 15, sub-section (1) of section 16 and section\n148 of the Central Goods and Services Tax Act, 2017 (12 of 2017), the Central Government, on the\nrecommendations of the Council, and on being satisfied that it is necessary in the public interest so to do, hereby\nmakes the following further amendments in the notification of the Government of India, in the Ministry of Finance\n(Department of Revenue) No.11/2017- Central Tax (Rate), dated the 28th June, 2017, published in the Gazette of\nIndia, Extraordinary, Part II, Section 3, Sub-section (i), vide number G.S.R. 690(E), dated the 28th June, 2017,\nnamely:-\n2. In the said notification, in the Table, against serial number 3, in column (3), in item (iv), after clause\n(f), the following shall be inserted, namely, -\n“ Provided that during the period beginning from the 14th June, 2021 and ending with the 30th\nSeptember, 2021, the central tax on service of description as specified in clause (f), shall, irrespective\nof rate specified in column (4), be levied at the rate of 2.5 per cent.’’.\n[F.No. CBIC-190354/63/2021-TO(TRU-I)-CBEC]\n(Rajeev Ranjan)\nUnder Secretary to the Government of India\nNote: - The principal notification No. 11/2017 - Central Tax (Rate), dated the 28th June, 2017 was published in\nthe Gazette of India, Extraordinary, vide number G.S.R. 690 (E), dated the 28th June, 2017 and was last amended\nby notification No. 02/2021 - Central Tax (Rate), dated the 2nd June, 2021 vide number G.S.R.377 (E), dated the\n2nd June, 2021.",
  "latest_effective_date": "2021-06-14",
  "file_paths": [
    "data\\notifications\\Central tax\\Central Tax 2021\\notfctn-04-central-tax-english-2021.pdf",
    "data\\notifications\\Central Tax (Rate)\\2021\\download (2).pdf"
  ]
}