{
  "group_id": "Integrated Tax::03/2021",
  "tax_type": "Integrated Tax",
  "notification_no": "03/2021",
  "documents": [
    {
      "document_nature": "original",
      "issued_on": "2021-06-02",
      "identity_source": "pdf",
      "file_path": "data\\notifications\\Integrated Tax (Rate)\\2021\\notfctn-03-2021-igst-rate-english.pdf"
    },
    {
      "document_nature": "original",
      "issued_on": "2021-06-02",
      "identity_source": "pdf",
      "file_path": "data\\notifications\\Integrated Tax\\2021\\notfctn-3-2021-igst-english.pdf"
    }
  ],
  "composite_text": "[ORIGINAL | Issued: 2021-06-02 | Source: notfctn-03-2021-igst-rate-english.pdf]\n[PAGE 1]\n[TO BE PUBLISHED IN THE GAZETTE OF INDIA, EXTRAORDINARY, PART II, SECTION 3, SUB-\nSECTION (i)]\nGovernment of India\nMinistry of Finance\n(Department of Revenue)\nNotification No. 03/2021-Integrated Tax (Rate)\nNew Delhi, the 2nd June, 2021\nG.S.R......(E).- In exercise of the powers conferred by section 20 of the Integrated Goods and Services Tax\nAct, 2017 (13 of 2017) read with section 148 of the Central Goods and Services Tax Act, 2017 (12 of 2017), the\nCentral Government, on the recommendations of the Council, and on being satisfied that it is necessary in the\npublic interest so to do, hereby makes the following amendments in the notification of the Government of India, in\nthe Ministry of Finance (Department of Revenue) No.06/2019- Integrated Tax (Rate), dated the 29th March, 2019,\npublished in the Gazette of India, Extraordinary, Part II, Section 3, Sub-section (i), vide number G.S.R. 259(E),\ndated the 29thMarch, 2019, namely:-\nIn the said notification, in the first paragraph,-\n(a) for the words “in whose case the liability to”, the words “, who shall” shall be substituted;\n(b) for the words “shall arise on the date of issuance of completion certificate for the project, where\nrequired, by the competent authority or on its first occupation, whichever is earlier”, the words “in a\ntax period not later than the tax period in which the date of issuance of the completion certificate for\nthe project, where required, by the competent authority, or the date of its first occupation, whichever is\nearlier, falls” shall be substituted.\n2. This notification shall come into force with effect from the 2nd day of June, 2021.\n[F. No. 354/53/2021-TRU]\n(Rajeev Ranjan)\nUnder Secretary to the Government of India\nNote: -The principal notification No. 06/2019 - Integrated Tax (Rate), dated the 29th March, 2019 was published\nin the Gazette of India, Extraordinary, vide number G.S.R. 259(E), dated the 29th March, 2019.\n1\n\n[ORIGINAL | Issued: 2021-06-02 | Source: notfctn-3-2021-igst-english.pdf]\n[PAGE 1]\n[TO BE PUBLISHED IN THE GAZZETE OF INDIA, EXTRAORDINARY, PART II, SECTION 3, SUB-\nSECTION (i)]\nGovernment of India\nMinistry of Finance\n(Department of Revenue)\nNotification No. 03/2021- Integrated Tax\nNew Delhi, the 2nd June, 2021\nG.S.R......(E).- In exercise of the powers conferred by sub-section (13) of section 13 of the Integrated Goods and\nServices Tax Act, 2017 (13 of 2017), the Central Government, on being satisfied that it is necessary in order to\nprevent double taxation or non-taxation of the supply of a service, or for the uniform application of rules, on the\nrecommendations of the Council, hereby makes the following further amendments in the notification of the\nGovernment of India, in the Ministry of Finance (Department of Revenue), No.4/2019- Integrated Tax, dated the\n30th September, 2019, published in the Gazette of India, Extraordinary, Part II, Section 3, Sub-section (i), vide\nnumber G.S.R. 748 (E), dated the 30th September, 2019, namely:-\nIn the said notification, in Table A, after serial number (2) and the entries relating thereto, the following serial\nnumber and entry shall be inserted, namely: -\n(1) (2) (3)\n“3 Supply of maintenance, repair or The place of supply of services\noverhaul service in respect of shall be the location of the\nships and other vessels, their recipient of service.”\nengines and other components or\nparts supplied to a person for use\nin the course or furtherance of\nbusiness\n2. This notification shall come into force with effect from the 2nd day of June, 2021.\n[F. No. 354/53/2021]\nRajeev Ranjan)\nUnder Secretary to the Government of India\nNote: - The principal notification No. 04/2019 - Integrated Tax, dated the 30th September, 2019 was published in\nthe Gazette of India, Extraordinary, vide number G.S.R. 748 (E), dated the 30th September, 2019 and was last\namended by notification No. 02/2020 – Integrated Tax, dated the 26th March, 2020 vide number G.S.R. 224 (E),\ndated the 26th March, 2020.",
  "latest_effective_date": "2021-06-02",
  "file_paths": [
    "data\\notifications\\Integrated Tax (Rate)\\2021\\notfctn-03-2021-igst-rate-english.pdf",
    "data\\notifications\\Integrated Tax\\2021\\notfctn-3-2021-igst-english.pdf"
  ]
}