{
  "group_id": "Union Territory Tax::35/2017",
  "tax_type": "Union Territory Tax",
  "notification_no": "35/2017",
  "documents": [
    {
      "document_nature": "original",
      "issued_on": "2017-10-13",
      "identity_source": "pdf",
      "file_path": "data\\notifications\\Union Territory Tax (Rate)\\2017\\notfctn-35-UTGST-rate-english.pdf"
    }
  ],
  "composite_text": "[ORIGINAL | Issued: 2017-10-13 | Source: notfctn-35-UTGST-rate-english.pdf]\n[PAGE 1]\n[TO BE PUBLISHED IN THE GAZETTE OF INDIA, EXTRAORDINARY, PART II,\nSECTION 3, SUB-SECTION (i)]\nGOVERNMENT OF INDIA\nMINISTRY OF FINANCE\n(Department of Revenue)\nNotification No. 35/2017- Union Territory Tax (Rate)\nNew Delhi, the 13th October, 2017\nG.S.R. (E).- In exercise of the powers conferred by sub-section (1) of section 8 of the\nUnion Territory Goods and Services Tax Act, 2017 (14 of 2017), the Central Government,\nbeing satisfied that it is necessary in the public interest so to do, on the recommendations of\nthe Council, hereby makes the following amendments in the notification of the Government\nof India in the Ministry of Finance (Department of Revenue), No.2/2017-Union territory Tax\n(Rate), dated the 28th June, 2017, published in the Gazette of India, Extraordinary, Part II,\nSection 3, Sub-section (i), vide number G.S.R. 711(E), dated the 28th June, 2017, namely:-\nIn the said notification,-\n(A) in the Schedule,-\n(i) after S. No. 122 and the entries relating thereto, the following serial number and\nthe entries shall be inserted, namely: -\n“122A 4907 Duty Credit Scrips”;\n(ii) after S. No. 149 and the entries relating thereto, the following serial number and\nthe entries shall be inserted, namely: -\n“150 - Supply of goods by a Government entity to Central\nGovernment, State Government, Union territory,\nlocal authority or any person specified by Central\nGovernment, State Government, Union territory or\nlocal authority, against consideration received from\nCentral Government, State Government, Union\nterritory or local authority in the form of grants”;\n(B) in the Explanation, after clause (iv), the following clause shall be inserted, namely:-\n“(v) The phrase “Government Entity” shall mean an authority or a board or any other\nbody including a society, trust, corporation, which is:\n(a) set up by an Act of Parliament or State Legislature; or\n(b) established by any Government,\nwith 90 percent or more participation by way of equity or control, to carry out a\n\n[PAGE 2]\nfunction entrusted by the Central Government, State government, Union territory or a\nlocal authority.”.\n(C) in ANNEXURE I, after point (b), the following proviso shall be inserted\n“Provided that, if the person having an actionable claim or enforceable right on a\nbrand name and the person undertaking packing of such goods in unit containers are\ntwo different persons, then the person having an actionable claim or enforceable right\non a brand name shall file an affidavit to that effect with the jurisdictional\nCommissioner of Central tax or jurisdictional officer of Union Territory tax, of the\nperson undertaking packing of such goods that he is voluntarily foregoing his\nactionable claim or enforceable right on such brand name as defined in Explanation\n(ii)(a); and he has authorised the person [undertaking packing of such goods in unit\ncontainers bearing said brand name] to print on such unit containers in indelible ink,\nboth in English and the local language, that in respect of such brand name he [the\nperson owning the brand name] is voluntarily foregoing the actionable claim or\nenforceable right voluntarily on such brand name.”\n[F.No.354/117/2017-TRU (Pt. III)]\n(Ruchi Bisht)\nUnder Secretary to the Government of India\nNote: - The principal notification No.2/2017- Union Territory Tax (Rate), dated the 28th\nJune, 2017 was published in the Gazette of India, Extraordinary, Part II, Section 3, Sub-\nsection (i) vide number G.S.R. 711(E), dated the 28th June, 2017 and last amended by\nNotification No. 28/2017- Union Territory Tax(Rate) dated 22nd September, 2017 published\nin the Gazette of India, Extraordinary, Part II, Section 3, Sub-section (i), vide number GSR\n1196 (E), dated the 22nd September, 2017.",
  "latest_effective_date": "2017-10-13",
  "file_paths": [
    "data\\notifications\\Union Territory Tax (Rate)\\2017\\notfctn-35-UTGST-rate-english.pdf"
  ]
}