{
  "group_id": "Union Territory Tax::15/2022",
  "tax_type": "Union Territory Tax",
  "notification_no": "15/2022",
  "documents": [
    {
      "document_nature": "original",
      "issued_on": "2017-06-28",
      "identity_source": "pdf",
      "file_path": "data\\notifications\\Union Territory Tax (Rate)\\2022\\gst-uttr15-2022.pdf"
    }
  ],
  "composite_text": "[ORIGINAL | Issued: 2017-06-28 | Source: gst-uttr15-2022.pdf]\n[PAGE 1]\n[TO BE PUBLISHED IN THE GAZETTE OF INDIA, EXTRAORDINARY, PART II, SECTION 3, SUB-\nSECTION (i)]\nGOVERNMENT OF INDIA\nMINISTRY OF FINANCE\n(DEPARTMENT OF REVENUE)\nNOTIFICATION No. 15/2022 -Union Territory Tax (Rate)\nNew Delhi, 30th December, 2022.\nG.S.R......(E).-In exercise of the powers conferred by sub-sections (3) and (4) of section 7, sub-section (1)\nand (3) of section 8 and clause (iv) and clause (xxvii) of section 21 of the Union territory Goods and Services Tax\nAct, 2017 (14 of 2017), read with sub-section (5) of section 15 and section 148 of the Central Goods and Services Tax\nAct, 2017 (12 of 2017), the Central Government, on being satisfied that it is necessary in the public interest so to do,\non the recommendations of the Council, hereby makes the following amendments further to amend the\nnotification of the Government of India, in the Ministry of Finance (Department of Revenue), No.12/2017-Union\nTerritory Tax (Rate), dated the 28th June, 2017, published in the Gazette of India, Extraordinary, Part II, Section 3,\nSub-section (i), vide number G.S.R. 703 (E), dated the 28th June, 2017, namely: -\nIn the said notification,\n(i) against S. No. 12, in column (3), after the entry, the following explanation shall be inserted, namely: -\n“Explanation. - For the purpose of exemption under this entry, this entry shall cover services by way of\nrenting of residential dwelling to a registered person where, –\n(v) the registered person is proprietor of a proprietorship concern and rents the residential\ndwelling in his personal capacity for use as his own residence; and\n(vi) such renting is on his own account and not that of the proprietorship concern.”;\n(ii) S. No. 23A and the entries relating thereto, shall be omitted.\n2. This notification shall come into force with effect from the 01st day of January, 2023.\n[F.No. CBIC-190354/316/2022-TRU Section-CBEC]\n(Rajeev Ranjan)\nUnder Secretary\nNote: The principal notification was published in the Gazette of India, Extraordinary, vide Notification No. 12/2017\n– Union Territory Tax (Rate), dated the 28th June, 2017, vide number G.S.R. 703 (E), dated the 28th June, 2017 and\nlast amended by notification No. 04/2022 – Union Territory Tax (Rate), dated the 13th July, 2022 vide number G.S.R.\n546(E), dated the 13th July, 2022.",
  "latest_effective_date": "2017-06-28",
  "file_paths": [
    "data\\notifications\\Union Territory Tax (Rate)\\2022\\gst-uttr15-2022.pdf"
  ]
}