{
  "source_file": "05_ENG.pdf",
  "file_path": "data\\notifications\\Central tax\\Central Tax 2023\\05_ENG.pdf",
  "file_hash": "e288147e1e7b7d10bd21a85445430c97b344e75ddb4f0b63b029b4b1e57c3934",
  "total_pages": 1,
  "pages": [
    {
      "page_no": 1,
      "text": "[TO BE PUBLISHED IN THE GAZETTE OF INDIA, EXTRAORDINARY, PART II, SECTION 3, SUB-\nSECTION (i)]\nGOVERNMENT OF INDIA\nMINISTRY OF FINANCE\n(DEPARTMENT OF REVENUE)\nCENTRAL BOARD OF INDIRECT TAXES AND CUSTOMS\nNOTIFICATION\nNo. 05/2023- Central Tax\nNew Delhi, dated the 31st March, 2023\nG.S.R.…(E).— In pursuance of the powers conferred by sub-rule (4B) of rule 8 of the Central Goods and Services Tax\nRules, 2017, the Central Government, on the recommendations of the Council, hereby makes the following amendment\nin the notification of the Government of India, the Ministry of Finance (Department of Revenue) No. 27/2022-Central\nTax, dated the 26th December, 2022 published in the Gazette of India, Extraordinary, Part II, Section 3, Sub-section\n(i), vide number G.S.R. 903(E), dated the 26th December, 2022, namely:-\nIn the said notification, for the words, “provisions of”, the words “proviso to” shall be substituted.\n2. They shall be deemed to have come into force from the 26th day of December,2022.\n[F. No. CBIC-20013/1/2023-GST]\n(Alok Kumar)\nDirector\nNote: - The principal Notification No. 27/2022- Central Tax, dated the 26th December, 2022, was published in the\nGazette of India, Extraordinary, Part II, Section 3, Sub-section (i), vide number G.S.R. 903(E), dated the 26th\nDecember, 2022."
    }
  ]
}