{
  "source_file": "download (38).pdf",
  "file_path": "data\\notifications\\Central tax\\Central Tax 2017\\download (38).pdf",
  "file_hash": "c29e20633414ef4144dac562d8c192568ed8af099adb21d77b064b10a7f8cf8f",
  "total_pages": 2,
  "pages": [
    {
      "page_no": 1,
      "text": "[To be published in the Gazette of India, Extraordinary, Part II, Section 3, Sub-section\n(i)]\nGovernment of India\nMinistry of Finance\nDepartment of Revenue\nCentral Board of Excise and Customs\nNotification No. 47/2017 – Central Tax\nNew Delhi, the 18th October, 2017\nG.S.R……(E):- In exercise of the powers conferred by section 164 of the Central Goods and\nServices Tax Act, 2017 (12 of 2017), the Central Government hereby makes the following\nrules further to amend the Central Goods and Services Tax Rules, 2017, namely:-\n(1) These rules may be called the Central Goods and Services Tax (Tenth Amendment)\nRules, 2017.\n(2) They shall come into force on the date of their publication in the Official Gazette.\n2. In the Central Goods and Services Tax Rules, 2017, –\n(i) in rule 89, insub-rule (1), for third proviso, the following proviso shall be substituted,\nnamely:-\n“Provided also that in respect of supplies regarded as deemed exports, the application\nmay be filed by, -\n(a) the recipient of deemed export supplies; or\n(b) the supplier of deemed export supplies in cases where the recipient does not avail\nof input tax credit on such supplies and furnishes an undertaking to the effect that the\nsupplier may claim the refund”;\n(ii) in rule 96A, in sub-rule (1), in clause (a),after the words “after the expiry of three\nmonths”, the words “, or such further period as may be allowed by the Commissioner,”\nshall be inserted;\n(iii) in FORM GST RFD-01,\n(a) for “Statement-2”, the following Statement shall be substituted, namely:-\n“Statement- 2 [rule 89(2)(c)]\nRefund Type: Exports of services with payment of tax\n(Amount in Rs.)\nSr. Invoice details Integrated tax Cess BRC/ FIRC Integrated Integrated Net\nNo. No. Date Value Taxable Amt. No. Date tax and tax and Integrated\nvalue cess cess tax and\ninvolved involved cess\nin debit in credit (6+7+10 -\nnote, if note, if 11)"
    },
    {
      "page_no": 2,
      "text": "any any\n1 2 3 4 5 6 7 8 9 10 11 12\n”;\n(b) for “Statement-4”, the following Statement shall be substituted, namely:-\n“Statement-4 [rule 89(2)(d) and 89(2)(e)]\nRefund Type: On account of supplies made to SEZ unit or SEZ Developer (on payment of\ntax)\n(Amount in Rs.)\nGSTIN Invoice details Shipping Integrated Tax Cess Integrated Integrated Net\nof bill/ Bill of tax and tax and Integrated\nrecipient export/ cess cess tax and\nEndorsed involved involved cess\ninvoice by in debit in credit (8+9+10–\nSEZ note, if note, if 11)\nNo. Date Value No. Date Taxable Amt. any any\nValue\n1 2 3 4 5 6 7 8 9 10 11 12\n.”\n[F. No. 349/58/2017-GST(Pt.)]\n(Gunjan Kumar Verma)\nUnder Secretary to the Government of India\nNote:- The principal rules were published in the Gazette of India, Extraordinary, Part II,\nSection 3, sub-section (i) vide notification No. 3/2017-Central Tax, dated the 19thJune,2017,\npublished vide number G.S.R 610 (E), dated the 19thJune, 2017 and last amended vide\nnotification No. 45/2017-Central Tax, dated the 13th October, 2017, published vide number\nG.S.R 1251 (E), dated the 13th October, 2017."
    }
  ]
}